Workbook

Sheet Summary
A1: Section | B1: Total $ | C1: of which estimated $
A2: Chips | B2: =SUMIF(Cost!A2:A55,A2,Cost!F2:F55) | C2: =SUMIFS(Cost!F2:F55,Cost!A2:A55,A2,Cost!H2:H55,"estimate")
A3: Controls | B3: =SUMIF(Cost!A2:A55,A3,Cost!F2:F55) | C3: =SUMIFS(Cost!F2:F55,Cost!A2:A55,A3,Cost!H2:H55,"estimate")
A4: Connectors | B4: =SUMIF(Cost!A2:A55,A4,Cost!F2:F55) | C4: =SUMIFS(Cost!F2:F55,Cost!A2:A55,A4,Cost!H2:H55,"estimate")
A5: Passives | B5: =SUMIF(Cost!A2:A55,A5,Cost!F2:F55) | C5: =SUMIFS(Cost!F2:F55,Cost!A2:A55,A5,Cost!H2:H55,"estimate")
A6: Power | B6: =SUMIF(Cost!A2:A55,A6,Cost!F2:F55) | C6: =SUMIFS(Cost!F2:F55,Cost!A2:A55,A6,Cost!H2:H55,"estimate")
A7: Modules | B7: =SUMIF(Cost!A2:A55,A7,Cost!F2:F55) | C7: =SUMIFS(Cost!F2:F55,Cost!A2:A55,A7,Cost!H2:H55,"estimate")
A8: PCBs | B8: =SUMIF(Cost!A2:A55,A8,Cost!F2:F55) | C8: =SUMIFS(Cost!F2:F55,Cost!A2:A55,A8,Cost!H2:H55,"estimate")
A9: Case | B9: =SUMIF(Cost!A2:A55,A9,Cost!F2:F55) | C9: =SUMIFS(Cost!F2:F55,Cost!A2:A55,A9,Cost!H2:H55,"estimate")
A10: Knobs | B10: =SUMIF(Cost!A2:A55,A10,Cost!F2:F55) | C10: =SUMIFS(Cost!F2:F55,Cost!A2:A55,A10,Cost!H2:H55,"estimate")
A11: Controller | B11: =SUMIF(Cost!A2:A55,A11,Cost!F2:F55) | C11: =SUMIFS(Cost!F2:F55,Cost!A2:A55,A11,Cost!H2:H55,"estimate")
A12: Shipping | B12: =SUMIF(Cost!A2:A55,A12,Cost!F2:F55) | C12: =SUMIFS(Cost!F2:F55,Cost!A2:A55,A12,Cost!H2:H55,"estimate")
A13: TOTAL | B13: =SUM(B2:B12) | C13: =SUM(C2:C12)
A15: Budget target (standard tier) | B15: 300
A16: Over budget | B16: =B13-B15
A18: Yellow rows on the Cost sheet are estimates; white rows are prices read on 2026-10-27; green rows Omer already owns.
A19: Not included: sales tax, solder/tools, spares, the optional 24LC32A EEPROM.

Sheet Cost
A1: Section | B1: Item | C1: Part / note | D1: Qty | E1: Unit $ | F1: Total $ | G1: Where | H1: Price
A2: Chips | B2: Mic preamp | C2: THAT1512P08-U (4 strips) | D2: 4 | E2: 5.84 | F2: =D2*E2 | G2: Mouser | H2: live
A3: Chips | B3: Op-amps | C3: NE5532P (12 strips + 4 master + 8 stereo) | D3: 24 | E3: 0.55 | F3: =D3*E3 | G3: Tayda | H3: estimate
A4: Chips | B4: Comparators | C4: LM393 (4 strips + 4 stereo) | D4: 8 | E4: 0.35 | F4: =D4*E4 | G4: Tayda | H4: estimate
A5: Chips | B5: Peak op-amp | C5: TL072CP (master) | D5: 1 | E5: 0.6 | F5: =D5*E5 | G5: Tayda | H5: estimate
A6: Chips | B6: Balanced line drivers | C6: TI DRV134PA (master) | D6: 2 | E6: 6.5 | F6: =D6*E6 | G6: Mouser | H6: estimate
A7: Chips | B7: Headphone amp | C7: NJM4556AD (master) | D7: 1 | E7: 1.52 | F7: =D7*E7 | G7: DigiKey | H7: live
A8: Chips | B8: Meter drivers | C8: LM3915N-1 or NTE1509 (master) | D8: 2 | E8: 7 | F8: =D8*E8 | G8: Jameco / Mouser | H8: estimate
A9: Chips | B9: MIDI opto, reverb LDO + op-amp | C9: 6N138, MCP1700-3302E, MCP6002-I/P | D9: 1 | E9: 2 | F9: =D9*E9 | G9: DigiKey | H9: estimate
A10: Chips | B10: IC sockets | C10: 43x DIP-8 + 2x DIP-18 | D10: 1 | E10: 3.5 | F10: =D10*E10 | G10: Tayda | H10: estimate
A11: Controls | B11: Fader, mono strips | C11: Bourns PTA6043-2015DPA103 60 mm | D11: 4 | E11: 2.37 | F11: =D11*E11 | G11: DigiKey | H11: live
A12: Controls | B12: Fader, dual (master + 2 stereo) | C12: Bourns PTA6044-2015DPA103 (DigiKey: 2000 MOQ, buy at Mouser/Utmel) | D12: 3 | E12: 2.7 | F12: =D12*E12 | G12: Mouser / Utmel | H12: estimate
A13: Controls | B13: Pot A10K single | C13: Alpha RD901F-40-15R1-A10K (Tayda A-1856) | D13: 14 | E13: 1.29 | F13: =D13*E13 | G13: Tayda | H13: live
... A55: Shipping | B55: Jameco | C55: Ground | D55: 1 | E55: 9 | F55: =D55*E55 | G55: Jameco | H55: estimate
